meta_translate/__init__.py
meta_translate/translate.py
meta_translate-0.0.1.dist-info/METADATA
meta_translate-0.0.1.dist-info/WHEEL
meta_translate-0.0.1.dist-info/top_level.txt
meta_translate-0.0.1.dist-info/RECORD
