Metadata-Version: 2.1
Name: meta-translate
Version: 0.0.1
Author: TAWSIF AHMED
Author-email: sleeping4cat@outlook.com
Requires-Dist: transformers
Requires-Dist: sentencepiece
Requires-Dist: torch
